Metadata-Version: 1.0
Name: GroupLasso
Version: 0.1.0
Summary: Group Lasso package for Python
Home-page: https://github.com/AnchorBlues/GroupLasso
Author: Yu Umegaki
Author-email: yu.umegaki@gmail.com
License: Copyright (c) 2018, Yu Umegaki
